setup.cfg
setup.py
pyrekall/__about__.py
pyrekall/__init__.py
pyrekall/main.py
pyrekall.egg-info/PKG-INFO
pyrekall.egg-info/SOURCES.txt
pyrekall.egg-info/dependency_links.txt
pyrekall.egg-info/not-zip-safe
pyrekall.egg-info/requires.txt
pyrekall.egg-info/top_level.txt