Metadata-Version: 1.1
Name: pyrekall
Version: 0.0
Summary: A wrapper for the Rekall framework
Home-page: https://github.com/TylerJFisher/pyrekall
Author: Tyler J. Fisher
Author-email: tyler@tylerfisher.org
License: MIT
Download-URL: https://github.com/TylerJFisher/pyrekall/tarball/0.1
Platform: UNKNOWN
